fleter/__init__.py
fleter/buttons.py
fleter/controls.py
fleter/icons_browser.py
fleter_demo/__init__.py
fleter_designer/__init__.py
fleter_designer/__main__.py
fleter-0.3.0.dist-info/METADATA
fleter-0.3.0.dist-info/WHEEL
fleter-0.3.0.dist-info/entry_points.txt
fleter-0.3.0.dist-info/top_level.txt
fleter-0.3.0.dist-info/RECORD
