Metadata-Version: 2.1
Name: fleter
Version: 0.3.0
Summary: flet extension library
Author: XiangQinxi
Author-email: XiangQinxi@outlook.com
Classifier: Programming Language :: Python :: 3
Classifier: License :: OSI Approved :: MIT License
Classifier: Operating System :: OS Independent
Requires-Python: >=3.7
Requires-Dist: flet (>=0.5.2)
